<annotation><folder>test</folder><filename>1 (1)_0_6047.jpeg</filename><path>C:\Users\kbonwitt\Desktop\object_detection1\object_detection1\data\images\train\1 (1)_0_6047.jpeg</path><source><database>Unknown</database></source><size><width>800</width><height>600</height><depth>3</depth></size><segmented>0</segmented><object><name>doritos</name><pose>Unspecified</pose><truncated>0</truncated><difficult>0</difficult><bndbox><xmin>259.44902896881104</xmin><ymin>101.30780339241028</ymin><xmax>606.8674087524414</xmax><ymax>472.35560417175293</ymax></bndbox></object></annotation>