<annotation><folder>test</folder><filename>1 (7)_0_8455.jpeg</filename><path>C:\Users\kbonwitt\Desktop\object_detection1\object_detection1\data\images\train\1 (7)_0_8455.jpeg</path><source><database>Unknown</database></source><size><width>800</width><height>600</height><depth>3</depth></size><segmented>0</segmented><object><name>doritos</name><pose>Unspecified</pose><truncated>0</truncated><difficult>0</difficult><bndbox><xmin>201.49998664855957</xmin><ymin>136.61423921585083</ymin><xmax>573.9776611328125</xmax><ymax>558.5145592689514</ymax></bndbox></object></annotation>