<annotation><folder>test</folder><filename>3 (21)_0_2619.jpeg</filename><path>C:\Users\kbonwitt\Desktop\object_detection1\object_detection1\data\images\train\3 (21)_0_2619.jpeg</path><source><database>Unknown</database></source><size><width>800</width><height>600</height><depth>3</depth></size><segmented>0</segmented><object><name>m&amp;m</name><pose>Unspecified</pose><truncated>0</truncated><difficult>0</difficult><bndbox><xmin>119.04659271240234</xmin><ymin>83.90718698501587</ymin><xmax>572.395658493042</xmax><ymax>544.2326188087463</ymax></bndbox></object></annotation>