<annotation><folder>test</folder><filename>3 (7)_0_6794.jpeg</filename><path>C:\Users\kbonwitt\Desktop\object_detection1\object_detection1\data\images\train\3 (7)_0_6794.jpeg</path><source><database>Unknown</database></source><size><width>800</width><height>600</height><depth>3</depth></size><segmented>0</segmented><object><name>m&amp;m</name><pose>Unspecified</pose><truncated>0</truncated><difficult>0</difficult><bndbox><xmin>322.3970890045166</xmin><ymin>55.746978521347046</ymin><xmax>528.3366680145264</xmax><ymax>459.1629981994629</ymax></bndbox></object></annotation>